HISTORY.rst
LICENSE
MANIFEST.in
README.rst
setup.py
daemonocle/__init__.py
daemonocle/_utils.py
daemonocle/cli.py
daemonocle/core.py
daemonocle/exceptions.py
daemonocle/helpers.py
daemonocle.egg-info/PKG-INFO
daemonocle.egg-info/SOURCES.txt
daemonocle.egg-info/dependency_links.txt
daemonocle.egg-info/requires.txt
daemonocle.egg-info/top_level.txt